zensols/ngramdb/__init__.py
zensols/ngramdb/app.py
zensols/ngramdb/cli.py
zensols/ngramdb/config.py
zensols/ngramdb/db.py
zensols/ngramdb/down.py
zensols/ngramdb/resources/ngram-agg-postgres.sql
zensols/ngramdb/resources/ngram-postgres.sql
zensols/ngramdb/resources/ngram-sqlite.sql
zensols/ngramdb/resources/ngramdb-postgres.conf
zensols/ngramdb/resources/ngramdb-sqlite.conf
zensols.ngramdb-0.0.2.dist-info/LICENSE.txt
zensols.ngramdb-0.0.2.dist-info/METADATA
zensols.ngramdb-0.0.2.dist-info/WHEEL
zensols.ngramdb-0.0.2.dist-info/entry_points.txt
zensols.ngramdb-0.0.2.dist-info/top_level.txt
zensols.ngramdb-0.0.2.dist-info/RECORD
