Metadata-Version: 2.1
Name: zensols.ngramdb
Version: 0.0.2
Summary: Creates an SQLite database ngrams.
Home-page: https://github.com/plandes/ngramdb
Author: Paul Landes
Author-email: landes@mailc.net
License: UNKNOWN
Download-URL: https://github.com/plandes/ngramdb/releases/download/v0.0.2/zensols.ngramdb-0.0.2-py3-none-any.whl
Keywords: nlp
Platform: UNKNOWN
Requires-Dist: zensols.actioncli (>=1.0.17)
Requires-Dist: zensols.dbpg (>=0.0.1)
